ase_ga/__init__.py
ase_ga/convergence.py
ase_ga/cutandsplicepairing.py
ase_ga/data.py
ase_ga/element_crossovers.py
ase_ga/element_mutations.py
ase_ga/multiprocessingrun.py
ase_ga/offspring_creator.py
ase_ga/ofp_comparator.py
ase_ga/parallellocalrun.py
ase_ga/particle_comparator.py
ase_ga/particle_crossovers.py
ase_ga/particle_mutations.py
ase_ga/pbs_queue_run.py
ase_ga/population.py
ase_ga/relax_attaches.py
ase_ga/slab_operators.py
ase_ga/soft_mutation.py
ase_ga/standard_comparators.py
ase_ga/standardmutations.py
ase_ga/startgenerator.py
ase_ga/utilities.py
ase_ga/tools/get_all_candidates
ase_ga/tools/remove_from_queue
ase_ga-1.0.3.dist-info/METADATA
ase_ga-1.0.3.dist-info/WHEEL
ase_ga-1.0.3.dist-info/licenses/COPYING
ase_ga-1.0.3.dist-info/licenses/COPYING.LESSER
ase_ga-1.0.3.dist-info/licenses/LICENSE
ase_ga-1.0.3.dist-info/RECORD
